django_rgbfield-1.0.dist-info/DESCRIPTION.rst
django_rgbfield-1.0.dist-info/LICENSE.txt
django_rgbfield-1.0.dist-info/METADATA
django_rgbfield-1.0.dist-info/RECORD
django_rgbfield-1.0.dist-info/WHEEL
django_rgbfield-1.0.dist-info/metadata.json
django_rgbfield-1.0.dist-info/top_level.txt
rgbfield/__init__.py
rgbfield/fields.py
